{
    "10": {
        "1091": 501,
        "1043": 502,
        "1121": 503,
        "1131": 504,
        "1993": 505,
        "2021": 506,
        "2041": 507,
        "2061": 508,
        "4011": 509,
        "4201": 510,
        "4021": 511,
        "4071": 512,
        "4111": 513,
        "4141": 514,
        "4991": 515,
        "5011": 516,
        "5021": 517,
        "5041": 518,
        "5061": 519,
        "5064": 520,
        "5081": 521,
        "5091": 522,
        "5131": 523,
        "5992": 524,
        "6011": 525,
        "6022": 526,
        "7028": 527,
        "7021": 528,
        "8225": 529,
        "8232": 530,
        "8351": 531,
        "9021": 532,
        "9061": 533,
        "9081": 534,
        "9091": 535,
        "9094": 536,
        "9101": 537,
        "9131": 538,
        "9134": 539,
        "9151": 540,
        "9251": 541,
        "9254": 542,
        "9255": 543,
        "9257": 544,
        "10022": 545,
        "10031": 546,
        "10041": 547,
        "10051": 548,
        "10052": 549,
        "10071": 550,
        "10072": 551,
        "10091": 552,
        "11051": 553,
        "13011": 554,
        "13031": 555,
        "13061": 556,
        "15011": 557,
        "15021": 558,
        "15091": 559,
        "15991": 560,
        "17011": 561,
        "17031": 562,
        "19021": 563,
        "19051": 564,
        "19141": 565,
        "19171": 566,
        "20013": 567,
        "20991": 568,
        "21041": 569,
        "22011": 570,
        "22021": 571,
        "22041": 572,
        "22051": 573,
        "22063": 574,
        "22071": 575,
        "22081": 576,
        "22991": 577,
        "22994": 578,
        "49017": 579,
        "0": 580,
        "9013": 581,
        "10081": 582
    }
}